ctodd_python_lib_kafka-1.0.2.dist-info/LICENSE.txt
ctodd_python_lib_kafka-1.0.2.dist-info/METADATA
ctodd_python_lib_kafka-1.0.2.dist-info/RECORD
ctodd_python_lib_kafka-1.0.2.dist-info/WHEEL
ctodd_python_lib_kafka-1.0.2.dist-info/top_level.txt
kafka_helpers/__init__.py
kafka_helpers/kafka_admin_helpers.py
kafka_helpers/kafka_consumer_helpers.py
kafka_helpers/kafka_exceptions.py
kafka_helpers/kafka_general_helpers.py
kafka_helpers/kafka_producer_helpers.py
kafka_helpers/kafka_topic_helpers.py
kafka_helpers/tests/__init__.py
kafka_helpers/tests/test_kafka_consumer_helpers.py
kafka_helpers/tests/test_kafka_exceptions.py
kafka_helpers/tests/test_kafka_general_helpers.py
kafka_helpers/tests/test_kafka_producer_helpers.py
