Metadata-Version: 2.1
Name: ctodd-python-lib-kafka
Version: 1.0.2
Summary: Python utilities used for interacting with Apache Kafka
Home-page: https://github.com/ChristopherHaydenTodd/ctodd-python-lib-kafka
Author: Christopher H. Todd
Author-email: Christopher.Hayden.Todd@gmail.com
License: MIT
Keywords: python,libraries,Kafka,consumer,producer
Platform: UNKNOWN
Classifier: Development Status :: 5 - Production/Stable
Classifier: Intended Audience :: Developers
Classifier: Natural Language :: English
Classifier: Programming Language :: Python
Classifier: Programming Language :: Python :: 3
Classifier: Programming Language :: Python :: 3.6
Classifier: Programming Language :: Python :: 3.7
Classifier: Programming Language :: Python :: 3.8
Requires-Python: >3.6
Requires-Dist: simplejson
Requires-Dist: confluent-kafka
